watchup_py/__init__.py
watchup_py/client.py
watchup_py/middleware.py
watchup_py/utils.py
watchup_py-0.1.0.dist-info/licenses/LICENSE
watchup_py-0.1.0.dist-info/METADATA
watchup_py-0.1.0.dist-info/WHEEL
watchup_py-0.1.0.dist-info/top_level.txt
watchup_py-0.1.0.dist-info/RECORD
