Metadata-Version: 2.4
Name: watchup-py
Version: 0.1.0
Summary: Python SDK / error boundary for Watchup.site
Home-page: https://github.com/tomurashigaraki22/watchup-py
Author: Raphael Tomiwa
Author-email: devtomiwa9@gmail.com
Classifier: Programming Language :: Python :: 3
Classifier: Operating System :: OS Independent
Classifier: License :: OSI Approved :: MIT License
Requires-Python: >=3.9
License-File: LICENSE
Requires-Dist: requests>=2.28.0
Requires-Dist: Flask>=2.0.0
Dynamic: author
Dynamic: author-email
Dynamic: classifier
Dynamic: description
Dynamic: description-content-type
Dynamic: home-page
Dynamic: license-file
Dynamic: requires-dist
Dynamic: requires-python
Dynamic: summary
